LICENSE
README.md
setup.py
yaapt.torch.egg-info/PKG-INFO
yaapt.torch.egg-info/SOURCES.txt
yaapt.torch.egg-info/dependency_links.txt
yaapt.torch.egg-info/requires.txt
yaapt.torch.egg-info/top_level.txt
yaapt_torch/__init__.py
yaapt_torch/yaapt.py