Metadata-Version: 2.1
Name: yaapt.torch
Version: 1.0.0
Summary: YAAPT Pitch Tracking function in PyTorch 
Home-page: https://github.com/pchampio/yaapt.torch
Author: Pierre Champion
License: Apache 2.0
Keywords: pitch,F0,yaapt,pytorch,torch
Platform: UNKNOWN
Classifier: Development Status :: 4 - Beta
Classifier: Intended Audience :: Developers
Classifier: Topic :: Scientific/Engineering :: Artificial Intelligence
Classifier: License :: OSI Approved :: MIT License
Classifier: Programming Language :: Python :: 3.6
